{
  "libVersion": "2.25.0",
  "projectname": "%E5%B7%A7%E5%B7%A5%E8%89%BA%E5%A2%85",
  "condition": {},
  "setting": {
    "urlCheck": true,
    "coverView": false,
    "lazyloadPlaceholderEnable": false,
    "skylineRenderEnable": false,
    "preloadBackgroundData": false,
    "autoAudits": false,
    "useApiHook": true,
    "showShadowRootInWxmlPanel": false,
    "useStaticServer": false,
    "useLanDebug": false,
    "showES6CompileOption": false,
    "compileHotReLoad": true,
    "checkInvalidKey": true,
    "ignoreDevUnusedFiles": true,
    "bigPackageSizeSupport": false
  }
}